{
  "sell_houses_and_cottages": [
    {
      "alias": "owner",
      "name": "Владелец объявления",
      "fields": [
        "Собственник",
        "Агентство",
        "Застройщик",
        "Подрядчик",
        "Частный риелтор"
      ]
    },
    {
      "alias": "house_type",
      "name": "Тип дома",
      "fields": [
        "Дом",
        "Дача",
        "Таунхаус",
        "Коттедж",
        "Незавершенное строительство"
      ]
    },
    {
      "alias": "wall_material",
      "name": "Материал стен",
      "fields": [
        "Кирпич",
        "Брус",
        "Бревно",
        "сэндвич-панели",
        "Пеноблоки",
        "Газоблоки",
        "Эксперементальный материал",
        "Другое"
      ]
    },
    { "alias": "room_number", "name": "Количество комнат", "fields": "NULL" },
    { "alias": "home_area", "name": "Площадь дома", "fields": "NULL" },
    {
      "alias": "bathrooms_number",
      "name": "Количество санузлов",
      "fields": ["На улице", "В доме", "Несколько"]
    },
    {
      "alias": "communications",
      "name": "Коммуникации",
      "fields": ["Электричество", "Отопление", "Газ", "Водоснабжение"]
    },
    {
      "alias": "balcony_number",
      "name": "Количество балконов",
      "fields": ["Нет", "Балкон", "Лоджия", "2 и более"]
    },
    {
      "alias": "additionally",
      "name": "Дополнительно",
      "fields": ["Кондиционер", "Камин", "Бассейн", "Баня/сауна"]
    },
    { "alias": "garage", "name": "Гараж", "fields": ["Да", "Нет"] },
    {
      "alias": "electricity",
      "name": "Электричество",
      "fields": ["Нет", "Подключено", "Есть возможность подключения"]
    },
    {
      "alias": "heating",
      "name": "Отопление",
      "fields": ["Печное", "Газовое", "Электрическое", "Центральное"]
    },
    {
      "alias": "gas",
      "name": "Газ",
      "fields": ["Нет", "Подключено", "Есть возможность подключения"]
    },
    {
      "alias": "water_supply",
      "name": "Водоснабжение",
      "fields": ["Автономное", "Централизованное", "Нет"]
    },
    { "alias": "land_area", "name": "Площадь участка", "fields": "NULL" },
    {
      "alias": "tenure",
      "name": "Срок владения",
      "fields": ["До 3 лет", "От 3 до 5 лет", "Более 5 лет"]
    },
    { "alias": "build_year", "name": "Год постройки", "fields": "NULL" },
    { "alias": "number_of_storeys", "name": "Этажность", "fields": "NULL" },
    {
      "alias": "land_type",
      "name": "Тип земельного участка",
      "fields": [
        "Сельхоз",
        "Фермерское хозяйство",
        "Поселение",
        "Промназначение",
        "Инвестпроект"
      ]
    },
    {
      "alias": "sale_type",
      "name": "Тип продажи",
      "fields": ["Свободная", "Альтернативная", "Ипотека", "Рассрочка"]
    }
  ]
}
