{"alias": "make", "value": "Groz", "children": [{"alias": "model", "value": "Polarsun", "children": [{"alias": "generation", "value": "I (2008—н. в.)", "children": [{"alias": "modification", "value": "Базовая", "children": [{"alias": "yearfrom", "value": "2008"}, {"alias": "yearto", "value": "2021"}, {"alias": "make", "value": "Groz"}, {"alias": "model", "value": "Polarsun"}, {"alias": "generation", "value": "I (2008—н. в.)"}, {"alias": "fueltype", "value": "Бензин"}, {"alias": "drivetype", "value": "Задний"}, {"alias": "transmission", "value": "Механика"}, {"alias": "modification", "value": "Базовая"}, {"alias": "power", "value": "105"}, {"alias": "enginesize", "value": "2.2"}, {"alias": "bodytype", "value": "Фургон"}, {"alias": "doors", "value": "4"}, {"alias": "complectations", "children": [{"alias": "complectation", "value": "2.2 MT (105 л.с.)"}]}]}, {"alias": "modification", "value": "Базовая", "children": [{"alias": "yearfrom", "value": "2008"}, {"alias": "yearto", "value": "2021"}, {"alias": "make", "value": "Groz"}, {"alias": "model", "value": "Polarsun"}, {"alias": "generation", "value": "I (2008—н. в.)"}, {"alias": "fueltype", "value": "Дизель"}, {"alias": "drivetype", "value": "Задний"}, {"alias": "transmission", "value": "Механика"}, {"alias": "modification", "value": "Базовая"}, {"alias": "power", "value": "105"}, {"alias": "enginesize", "value": "2.2"}, {"alias": "bodytype", "value": "Фургон"}, {"alias": "doors", "value": "4"}, {"alias": "complectations", "children": [{"alias": "complectation", "value": "2.8 D MT (90 л.с.)"}]}]}, {"alias": "modification", "value": "Базовая", "children": [{"alias": "yearfrom", "value": "2008"}, {"alias": "yearto", "value": "2021"}, {"alias": "make", "value": "Groz"}, {"alias": "model", "value": "Polarsun"}, {"alias": "generation", "value": "I (2008—н. в.)"}, {"alias": "fueltype", "value": "Бензин"}, {"alias": "drivetype", "value": "Задний"}, {"alias": "transmission", "value": "Механика"}, {"alias": "modification", "value": "Базовая"}, {"alias": "power", "value": "105"}, {"alias": "enginesize", "value": "2.2"}, {"alias": "bodytype", "value": "Фургон"}, {"alias": "doors", "value": "5"}, {"alias": "complectations", "children": [{"alias": "complectation", "value": "2.2 MT (105 л.с.)"}]}]}, {"alias": "modification", "value": "Базовая", "children": [{"alias": "yearfrom", "value": "2008"}, {"alias": "yearto", "value": "2021"}, {"alias": "make", "value": "Groz"}, {"alias": "model", "value": "Polarsun"}, {"alias": "generation", "value": "I (2008—н. в.)"}, {"alias": "fueltype", "value": "Дизель"}, {"alias": "drivetype", "value": "Задний"}, {"alias": "transmission", "value": "Механика"}, {"alias": "modification", "value": "Базовая"}, {"alias": "power", "value": "105"}, {"alias": "enginesize", "value": "2.2"}, {"alias": "bodytype", "value": "Фургон"}, {"alias": "doors", "value": "5"}, {"alias": "complectations", "children": [{"alias": "complectation", "value": "2.8 D MT (90 л.с.)"}]}]}, {"alias": "modification", "value": "Базовая", "children": [{"alias": "yearfrom", "value": "2008"}, {"alias": "yearto", "value": "2021"}, {"alias": "make", "value": "Groz"}, {"alias": "model", "value": "Polarsun"}, {"alias": "generation", "value": "I (2008—н. в.)"}, {"alias": "fueltype", "value": "Бензин"}, {"alias": "drivetype", "value": "Задний"}, {"alias": "transmission", "value": "Механика"}, {"alias": "modification", "value": "Базовая"}, {"alias": "power", "value": "105"}, {"alias": "enginesize", "value": "2.2"}, {"alias": "bodytype", "value": "Минивэн"}, {"alias": "doors", "value": "4"}, {"alias": "complectations", "children": [{"alias": "complectation", "value": "2.2 MT (105 л.с.)"}]}]}, {"alias": "modification", "value": "Базовая", "children": [{"alias": "yearfrom", "value": "2008"}, {"alias": "yearto", "value": "2021"}, {"alias": "make", "value": "Groz"}, {"alias": "model", "value": "Polarsun"}, {"alias": "generation", "value": "I (2008—н. в.)"}, {"alias": "fueltype", "value": "Дизель"}, {"alias": "drivetype", "value": "Задний"}, {"alias": "transmission", "value": "Механика"}, {"alias": "modification", "value": "Базовая"}, {"alias": "power", "value": "105"}, {"alias": "enginesize", "value": "2.2"}, {"alias": "bodytype", "value": "Минивэн"}, {"alias": "doors", "value": "4"}, {"alias": "complectations", "children": [{"alias": "complectation", "value": "2.8 D MT (90 л.с.)"}]}]}]}]}]}