{"alias": "make", "value": "Piaggio", "children": [{"alias": "model", "value": "Porter", "children": [{"alias": "generation", "value": "I (1992—н. в.)", "children": [{"alias": "modification", "value": "1.3 MT (65 л.c.)", "children": [{"alias": "yearfrom", "value": "1992"}, {"alias": "yearto", "value": "2021"}, {"alias": "make", "value": "Piaggio"}, {"alias": "model", "value": "Porter"}, {"alias": "generation", "value": "I (1992—н. в.)"}, {"alias": "fueltype", "value": "Бензин"}, {"alias": "drivetype", "value": "Задний"}, {"alias": "transmission", "value": "Механика"}, {"alias": "modification", "value": "1.3 MT (65 л.c.)"}, {"alias": "power", "value": "65"}, {"alias": "enginesize", "value": "1.3"}, {"alias": "bodytype", "value": "Минивэн"}, {"alias": "doors", "value": "5"}, {"alias": "complectations", "children": [{"alias": "complectation", "value": "Базовая"}]}]}, {"alias": "modification", "value": "1.3 4WD MT (65 л.c.)", "children": [{"alias": "yearfrom", "value": "1992"}, {"alias": "yearto", "value": "2021"}, {"alias": "make", "value": "Piaggio"}, {"alias": "model", "value": "Porter"}, {"alias": "generation", "value": "I (1992—н. в.)"}, {"alias": "fueltype", "value": "Бензин"}, {"alias": "drivetype", "value": "Полный"}, {"alias": "transmission", "value": "Механика"}, {"alias": "modification", "value": "1.3 4WD MT (65 л.c.)"}, {"alias": "power", "value": "65"}, {"alias": "enginesize", "value": "1.3"}, {"alias": "bodytype", "value": "Минивэн"}, {"alias": "doors", "value": "5"}, {"alias": "complectations", "children": [{"alias": "complectation", "value": "Базовая"}]}]}, {"alias": "modification", "value": "1.2 D MT (64 л.c.)", "children": [{"alias": "yearfrom", "value": "1992"}, {"alias": "yearto", "value": "2021"}, {"alias": "make", "value": "Piaggio"}, {"alias": "model", "value": "Porter"}, {"alias": "generation", "value": "I (1992—н. в.)"}, {"alias": "fueltype", "value": "Дизель"}, {"alias": "drivetype", "value": "Задний"}, {"alias": "transmission", "value": "Механика"}, {"alias": "modification", "value": "1.2 D MT (64 л.c.)"}, {"alias": "power", "value": "64"}, {"alias": "enginesize", "value": "1.2"}, {"alias": "bodytype", "value": "Минивэн"}, {"alias": "doors", "value": "5"}, {"alias": "complectations", "children": [{"alias": "complectation", "value": "Базовая"}]}]}, {"alias": "modification", "value": "1.4 D MT (38 л.c.)", "children": [{"alias": "yearfrom", "value": "1992"}, {"alias": "yearto", "value": "2021"}, {"alias": "make", "value": "Piaggio"}, {"alias": "model", "value": "Porter"}, {"alias": "generation", "value": "I (1992—н. в.)"}, {"alias": "fueltype", "value": "Дизель"}, {"alias": "drivetype", "value": "Задний"}, {"alias": "transmission", "value": "Механика"}, {"alias": "modification", "value": "1.4 D MT (38 л.c.)"}, {"alias": "power", "value": "38"}, {"alias": "enginesize", "value": "1.4"}, {"alias": "bodytype", "value": "Минивэн"}, {"alias": "doors", "value": "5"}, {"alias": "complectations", "children": [{"alias": "complectation", "value": "Базовая"}]}]}, {"alias": "modification", "value": "1.2 D 4WD MT (64 л.c.)", "children": [{"alias": "yearfrom", "value": "1992"}, {"alias": "yearto", "value": "2021"}, {"alias": "make", "value": "Piaggio"}, {"alias": "model", "value": "Porter"}, {"alias": "generation", "value": "I (1992—н. в.)"}, {"alias": "fueltype", "value": "Дизель"}, {"alias": "drivetype", "value": "Полный"}, {"alias": "transmission", "value": "Механика"}, {"alias": "modification", "value": "1.2 D 4WD MT (64 л.c.)"}, {"alias": "power", "value": "64"}, {"alias": "enginesize", "value": "1.2"}, {"alias": "bodytype", "value": "Минивэн"}, {"alias": "doors", "value": "5"}, {"alias": "complectations", "children": [{"alias": "complectation", "value": "Базовая"}]}]}, {"alias": "modification", "value": "0.0 AT (14 л.c.)", "children": [{"alias": "yearfrom", "value": "1992"}, {"alias": "yearto", "value": "2021"}, {"alias": "make", "value": "Piaggio"}, {"alias": "model", "value": "Porter"}, {"alias": "generation", "value": "I (1992—н. в.)"}, {"alias": "fueltype", "value": "Электро"}, {"alias": "drivetype", "value": "Задний"}, {"alias": "transmission", "value": "Автомат"}, {"alias": "modification", "value": "0.0 AT (14 л.c.)"}, {"alias": "power", "value": "14"}, {"alias": "enginesize", "value": "0.0"}, {"alias": "bodytype", "value": "Минивэн"}, {"alias": "doors", "value": "5"}, {"alias": "complectations", "children": [{"alias": "complectation", "value": "Базовая"}]}]}, {"alias": "modification", "value": "1.0 MT (45 л.c.)", "children": [{"alias": "yearfrom", "value": "1992"}, {"alias": "yearto", "value": "2021"}, {"alias": "make", "value": "Piaggio"}, {"alias": "model", "value": "Porter"}, {"alias": "generation", "value": "I (1992—н. в.)"}, {"alias": "fueltype", "value": "Бензин"}, {"alias": "drivetype", "value": "Задний"}, {"alias": "transmission", "value": "Механика"}, {"alias": "modification", "value": "1.0 MT (45 л.c.)"}, {"alias": "power", "value": "45"}, {"alias": "enginesize", "value": "1.0"}, {"alias": "bodytype", "value": "Минивэн"}, {"alias": "doors", "value": "5"}, {"alias": "complectations", "children": [{"alias": "complectation", "value": "Базовая"}]}]}]}]}]}