{"alias": "make", "value": "W Motors", "children": [{"alias": "model", "value": "Fenyr SuperSport", "children": [{"alias": "generation", "value": "I (2015—н. в.)", "children": [{"alias": "modification", "value": "4.0 AMT (900 л.c.)", "children": [{"alias": "yearfrom", "value": "2015"}, {"alias": "yearto", "value": "2021"}, {"alias": "make", "value": "W Motors"}, {"alias": "model", "value": "Fenyr SuperSport"}, {"alias": "generation", "value": "I (2015—н. в.)"}, {"alias": "fueltype", "value": "Бензин"}, {"alias": "drivetype", "value": "Задний"}, {"alias": "transmission", "value": "Робот"}, {"alias": "modification", "value": "4.0 AMT (900 л.c.)"}, {"alias": "power", "value": "900"}, {"alias": "enginesize", "value": "4.0"}, {"alias": "bodytype", "value": "Купе"}, {"alias": "doors", "value": "2"}, {"alias": "complectations", "children": [{"alias": "complectation", "value": "Базовая"}]}]}]}]}, {"alias": "model", "value": "Lykan HyperSport", "children": [{"alias": "generation", "value": "I (2013—н. в.)", "children": [{"alias": "modification", "value": "3.8 AMT (770 л.c.)", "children": [{"alias": "yearfrom", "value": "2013"}, {"alias": "yearto", "value": "2021"}, {"alias": "make", "value": "W Motors"}, {"alias": "model", "value": "Lykan HyperSport"}, {"alias": "generation", "value": "I (2013—н. в.)"}, {"alias": "fueltype", "value": "Бензин"}, {"alias": "drivetype", "value": "Задний"}, {"alias": "transmission", "value": "Робот"}, {"alias": "modification", "value": "3.8 AMT (770 л.c.)"}, {"alias": "power", "value": "770"}, {"alias": "enginesize", "value": "3.7"}, {"alias": "bodytype", "value": "Купе"}, {"alias": "doors", "value": "2"}, {"alias": "complectations", "children": [{"alias": "complectation", "value": "Базовая"}]}]}, {"alias": "modification", "value": "3.8 MT (770 л.c.)", "children": [{"alias": "yearfrom", "value": "2013"}, {"alias": "yearto", "value": "2021"}, {"alias": "make", "value": "W Motors"}, {"alias": "model", "value": "Lykan HyperSport"}, {"alias": "generation", "value": "I (2013—н. в.)"}, {"alias": "fueltype", "value": "Бензин"}, {"alias": "drivetype", "value": "Задний"}, {"alias": "transmission", "value": "Механика"}, {"alias": "modification", "value": "3.8 MT (770 л.c.)"}, {"alias": "power", "value": "770"}, {"alias": "enginesize", "value": "3.7"}, {"alias": "bodytype", "value": "Купе"}, {"alias": "doors", "value": "2"}, {"alias": "complectations", "children": [{"alias": "complectation", "value": "Базовая"}]}]}]}]}]}